package/__init__.py
package/csv2md/__init__.py
package/csv2md/csv2md.py
package/tests/__init__.py
package/tests/test.py
pymdown_csv2md-3.0.0.dist-info/LICENSE
pymdown_csv2md-3.0.0.dist-info/METADATA
pymdown_csv2md-3.0.0.dist-info/WHEEL
pymdown_csv2md-3.0.0.dist-info/entry_points.txt
pymdown_csv2md-3.0.0.dist-info/top_level.txt
pymdown_csv2md-3.0.0.dist-info/RECORD
