Metadata-Version: 2.1
Name: pymdown-csv2md
Version: 3.0.0
Summary: A Python-Markdown extension for converting .csv file to markdown tables inline.
Home-page: https://github.com/mghweb/pymdown-csv2md
Author: Max Hegler
Author-email: maxghegler@gmail.com
License: MIT License
Platform: UNKNOWN
Classifier: Intended Audience :: Developers
Classifier: Programming Language :: Python :: 3
Classifier: License :: OSI Approved :: MIT License
Classifier: Operating System :: OS Independent
Classifier: Topic :: Software Development :: Libraries :: Python Modules
Classifier: Topic :: Text Processing :: Filters
Classifier: Topic :: Text Processing :: Markup :: HTML
Requires-Python: >3.0
License-File: LICENSE
Requires-Dist: csv2md (==1.1.2)
Requires-Dist: Markdown (==3.3.6)
